nonebot_plugin_genshin_calendar/__init__.py
nonebot_plugin_genshin_calendar/calendar_config.py
nonebot_plugin_genshin_calendar/res/__init__.py
nonebot_plugin_genshin_calendar/res/wqy-microhei.ttc
nonebot_plugin_genshin_calendar/util/__init__.py
nonebot_plugin_genshin_calendar/util/aiorequest.py
nonebot_plugin_genshin_calendar/util/draw.py
nonebot_plugin_genshin_calendar/util/event.py
nonebot_plugin_genshin_calendar/util/generate.py
nonebot_plugin_genshin_calendar-0.0.3.dist-info/LICENSE
nonebot_plugin_genshin_calendar-0.0.3.dist-info/METADATA
nonebot_plugin_genshin_calendar-0.0.3.dist-info/WHEEL
nonebot_plugin_genshin_calendar-0.0.3.dist-info/top_level.txt
nonebot_plugin_genshin_calendar-0.0.3.dist-info/RECORD
